.gitignore
LICENSE
Makefile
README.rst
jinja2rst.py
setup.py
bin/jinja2rst
examples/demo.css
jinja2rst.egg-info/PKG-INFO
jinja2rst.egg-info/SOURCES.txt
jinja2rst.egg-info/dependency_links.txt
jinja2rst.egg-info/top_level.txt
tests/__init__.py
tests/test_convert.py
tests/test_convert_leading_hash.py
tests/test_convert_single_line_comments.py