Metadata-Version: 1.1
Name: jinja2rst
Version: 0.1
Summary: A Simple Tool for Documenting Jinja2 Template-Files
Home-page: https://github.com/htgoebel/jinja2rst
Author: Hartmut Goebel
Author-email: h.goebel@crazy-compilers.com
License: GPLv3+
Download-URL: https://github.com/htgoebel/jinja2rst/releases
Keywords: jinja2,rst,reStructuresText,literate programming
Platform: UNKNOWN
Classifier: Development Status :: 4 - Beta
Classifier: Environment :: Console
Classifier: Intended Audience :: Developers
Classifier: Intended Audience :: System Administrators
Classifier: License :: OSI Approved :: GNU General Public License v3 or later (GPLv3+)
Classifier: Natural Language :: English
Classifier: Operating System :: OS Independent
Classifier: Programming Language :: Python :: 2 :: Only
Classifier: Topic :: Software Development :: Documentation
